avalAgent/agent.py
avalAgent/logger.py
avalagent-1.0.4.dist-info/licenses/LICENSE
avalagent-1.0.4.dist-info/METADATA
avalagent-1.0.4.dist-info/WHEEL
avalagent-1.0.4.dist-info/top_level.txt
avalagent-1.0.4.dist-info/RECORD
