Metadata-Version: 2.4
Name: avalAgent
Version: 1.0.4
Summary: AI agent wrapper for AvalAI API with retry and model fallback support
Author-email: Amirhossein Derhami <D3rhami@gmail.com>
License: MIT
Project-URL: AvalAi-Homepage, https://avalai.ir
Project-URL: Source, https://github.com/D3rhami/avalAgent
Project-URL: Bug-Reports, https://github.com/D3rhami/avalAgent/issues
Project-URL: Documentation, https://github.com/D3rhami/avalAgent#readme
Project-URL: Changelog, https://github.com/D3rhami/avalAgent/releases
Keywords: ai,chatbot,avalai,langchain,openai-wrapper
Classifier: Intended Audience :: Developers
Classifier: Programming Language :: Python :: 3
Classifier: Programming Language :: Python :: 3.9
Classifier: Programming Language :: Python :: 3.10
Classifier: Programming Language :: Python :: 3.11
Classifier: Operating System :: OS Independent
Classifier: License :: OSI Approved :: MIT License
Classifier: Topic :: Software Development :: Libraries :: Python Modules
Classifier: Topic :: Scientific/Engineering :: Artificial Intelligence
Requires-Python: >=3.11
License-File: LICENSE
Requires-Dist: pydantic>=2.0.0
Requires-Dist: requests>=2.25.0
Requires-Dist: langchain-core>=0.1.0
Requires-Dist: langchain-openai>=0.0.1
Requires-Dist: openai>=1.0.0
Requires-Dist: tabulate~=0.9.0
Dynamic: license-file
